haudiov/__init__.py
haudiov/ffmpeg.zip
haudiov/audio/__init__.py
haudiov/audio/data/__init__.py
haudiov/audio/data/convert.py
haudiov/audio/data/extract.py
haudiov/audio/data/merge.py
haudiov/audio/data/trim.py
haudiov/video/CodecHandler.py
haudiov/video/EffectsLibrary.py
haudiov/video/FrameAnalyzer.py
haudiov/video/MetadataEditor.py
haudiov/video/VideoProcessor.py
haudiov/video/__init__.py
haudiov/video/setup.py
haudiov-1.0.dist-info/licenses/LICENSE.txt
haudiov-1.0.dist-info/METADATA
haudiov-1.0.dist-info/WHEEL
haudiov-1.0.dist-info/top_level.txt
haudiov-1.0.dist-info/RECORD
