Metadata-Version: 2.4
Name: haudiov
Version: 1.0
Summary: haudiov
Author: huang yi yi
Author-email: 363766687@qq.com
Requires-Python: >=3.6
License-File: LICENSE.txt
Requires-Dist: pyaudio
Requires-Dist: numpy
Requires-Dist: pyfiglet
Dynamic: author
Dynamic: author-email
Dynamic: description
Dynamic: license-file
Dynamic: requires-dist
Dynamic: requires-python
Dynamic: summary
